{"nodes": [{"id": "d_fitme_lib_features_nutrition_widgets_log_sheet_dart", "label": "log_sheet.dart", "file_type": "code", "source_file": "D:\\fitme\\lib\\features\\nutrition\\widgets\\log_sheet.dart", "source_location": null}, {"id": "d_fitme_lib_features_nutrition_widgets_log_sheet_dart_logsheet", "label": "LogSheet", "file_type": "code", "source_file": "D:\\fitme\\lib\\features\\nutrition\\widgets\\log_sheet.dart", "source_location": null}, {"id": "d_fitme_lib_features_nutrition_widgets_log_sheet_dart_logsheetstate", "label": "_LogSheetState", "file_type": "code", "source_file": "D:\\fitme\\lib\\features\\nutrition\\widgets\\log_sheet.dart", "source_location": null}, {"id": "d_fitme_lib_features_nutrition_widgets_log_sheet_dart_searchresults", "label": "_SearchResults", "file_type": "code", "source_file": "D:\\fitme\\lib\\features\\nutrition\\widgets\\log_sheet.dart", "source_location": null}, {"id": "d_fitme_lib_features_nutrition_widgets_log_sheet_dart_recentstab", "label": "_RecentsTab", "file_type": "code", "source_file": "D:\\fitme\\lib\\features\\nutrition\\widgets\\log_sheet.dart", "source_location": null}, {"id": "d_fitme_lib_features_nutrition_widgets_log_sheet_dart_customstab", "label": "_CustomsTab", "file_type": "code", "source_file": "D:\\fitme\\lib\\features\\nutrition\\widgets\\log_sheet.dart", "source_location": null}, {"id": "d_fitme_lib_features_nutrition_widgets_log_sheet_dart_listheader", "label": "_ListHeader", "file_type": "code", "source_file": "D:\\fitme\\lib\\features\\nutrition\\widgets\\log_sheet.dart", "source_location": null}, {"id": "d_fitme_lib_features_nutrition_widgets_log_sheet_dart_custommealtile", "label": "_CustomMealTile", "file_type": "code", "source_file": "D:\\fitme\\lib\\features\\nutrition\\widgets\\log_sheet.dart", "source_location": null}, {"id": "d_fitme_lib_features_nutrition_widgets_log_sheet_dart_foodresulttile", "label": "_FoodResultTile", "file_type": "code", "source_file": "D:\\fitme\\lib\\features\\nutrition\\widgets\\log_sheet.dart", "source_location": null}, {"id": "d_fitme_lib_features_nutrition_widgets_log_sheet_dart_heartbutton", "label": "_HeartButton", "file_type": "code", "source_file": "D:\\fitme\\lib\\features\\nutrition\\widgets\\log_sheet.dart", "source_location": null}, {"id": "d_fitme_lib_features_nutrition_widgets_log_sheet_dart_show", "label": "show", "file_type": "code", "source_file": "D:\\fitme\\lib\\features\\nutrition\\widgets\\log_sheet.dart", "source_location": null}, {"id": "d_fitme_lib_features_nutrition_widgets_log_sheet_dart_initstate", "label": "initState", "file_type": "code", "source_file": "D:\\fitme\\lib\\features\\nutrition\\widgets\\log_sheet.dart", "source_location": null}, {"id": "d_fitme_lib_features_nutrition_widgets_log_sheet_dart_dispose", "label": "dispose", "file_type": "code", "source_file": "D:\\fitme\\lib\\features\\nutrition\\widgets\\log_sheet.dart", "source_location": null}, {"id": "d_fitme_lib_features_nutrition_widgets_log_sheet_dart_onsearchchanged", "label": "_onSearchChanged", "file_type": "code", "source_file": "D:\\fitme\\lib\\features\\nutrition\\widgets\\log_sheet.dart", "source_location": null}, {"id": "d_fitme_lib_features_nutrition_widgets_log_sheet_dart_onfoodtapped", "label": "_onFoodTapped", "file_type": "code", "source_file": "D:\\fitme\\lib\\features\\nutrition\\widgets\\log_sheet.dart", "source_location": null}, {"id": "d_fitme_lib_features_nutrition_widgets_log_sheet_dart_togglefav", "label": "_toggleFav", "file_type": "code", "source_file": "D:\\fitme\\lib\\features\\nutrition\\widgets\\log_sheet.dart", "source_location": null}, {"id": "d_fitme_lib_features_nutrition_widgets_log_sheet_dart_build", "label": "build", "file_type": "code", "source_file": "D:\\fitme\\lib\\features\\nutrition\\widgets\\log_sheet.dart", "source_location": null}, {"id": "d_fitme_lib_features_nutrition_widgets_log_sheet_dart_container", "label": "Container", "file_type": "code", "source_file": "D:\\fitme\\lib\\features\\nutrition\\widgets\\log_sheet.dart", "source_location": null}, {"id": "d_fitme_lib_features_nutrition_widgets_log_sheet_dart_sizedbox", "label": "SizedBox", "file_type": "code", "source_file": "D:\\fitme\\lib\\features\\nutrition\\widgets\\log_sheet.dart", "source_location": null}, {"id": "d_fitme_lib_features_nutrition_widgets_log_sheet_dart_padding", "label": "Padding", "file_type": "code", "source_file": "D:\\fitme\\lib\\features\\nutrition\\widgets\\log_sheet.dart", "source_location": null}, {"id": "d_fitme_lib_features_nutrition_widgets_log_sheet_dart_icon", "label": "Icon", "file_type": "code", "source_file": "D:\\fitme\\lib\\features\\nutrition\\widgets\\log_sheet.dart", "source_location": null}, {"id": "d_fitme_lib_features_nutrition_widgets_log_sheet_dart_spacer", "label": "Spacer", "file_type": "code", "source_file": "D:\\fitme\\lib\\features\\nutrition\\widgets\\log_sheet.dart", "source_location": null}, {"id": "d_fitme_lib_features_nutrition_widgets_log_sheet_dart_textstyle", "label": "TextStyle", "file_type": "code", "source_file": "D:\\fitme\\lib\\features\\nutrition\\widgets\\log_sheet.dart", "source_location": null}, {"id": "d_fitme_lib_features_nutrition_widgets_log_sheet_dart_center", "label": "Center", "file_type": "code", "source_file": "D:\\fitme\\lib\\features\\nutrition\\widgets\\log_sheet.dart", "source_location": null}, {"id": "d_fitme_lib_features_nutrition_widgets_log_sheet_dart_stack", "label": "Stack", "file_type": "code", "source_file": "D:\\fitme\\lib\\features\\nutrition\\widgets\\log_sheet.dart", "source_location": null}, {"id": "dart_async", "label": "dart:async", "file_type": "code", "source_file": "D:\\fitme\\lib\\features\\nutrition\\widgets\\log_sheet.dart", "source_location": null}, {"id": "package_flutter_material_dart", "label": "package:flutter/material.dart", "file_type": "code", "source_file": "D:\\fitme\\lib\\features\\nutrition\\widgets\\log_sheet.dart", "source_location": null}, {"id": "package_flutter_services_dart", "label": "package:flutter/services.dart", "file_type": "code", "source_file": "D:\\fitme\\lib\\features\\nutrition\\widgets\\log_sheet.dart", "source_location": null}, {"id": "package_flutter_riverpod_flutter_riverpod_dart", "label": "package:flutter_riverpod/flutter_riverpod.dart", "file_type": "code", "source_file": "D:\\fitme\\lib\\features\\nutrition\\widgets\\log_sheet.dart", "source_location": null}, {"id": "core_theme_app_theme_dart", "label": "../../../core/theme/app_theme.dart", "file_type": "code", "source_file": "D:\\fitme\\lib\\features\\nutrition\\widgets\\log_sheet.dart", "source_location": null}, {"id": "models_food_item_dart", "label": "../models/food_item.dart", "file_type": "code", "source_file": "D:\\fitme\\lib\\features\\nutrition\\widgets\\log_sheet.dart", "source_location": null}, {"id": "providers_nutrition_provider_dart", "label": "../providers/nutrition_provider.dart", "file_type": "code", "source_file": "D:\\fitme\\lib\\features\\nutrition\\widgets\\log_sheet.dart", "source_location": null}, {"id": "services_food_search_service_dart", "label": "../services/food_search_service.dart", "file_type": "code", "source_file": "D:\\fitme\\lib\\features\\nutrition\\widgets\\log_sheet.dart", "source_location": null}, {"id": "screens_quantity_selection_screen_dart", "label": "../screens/quantity_selection_screen.dart", "file_type": "code", "source_file": "D:\\fitme\\lib\\features\\nutrition\\widgets\\log_sheet.dart", "source_location": null}, {"id": "screens_favorites_screen_dart", "label": "../screens/favorites_screen.dart", "file_type": "code", "source_file": "D:\\fitme\\lib\\features\\nutrition\\widgets\\log_sheet.dart", "source_location": null}, {"id": "barcode_scanner_screen_dart", "label": "barcode_scanner_screen.dart", "file_type": "code", "source_file": "D:\\fitme\\lib\\features\\nutrition\\widgets\\log_sheet.dart", "source_location": null}, {"id": "custom_meal_form_dart", "label": "custom_meal_form.dart", "file_type": "code", "source_file": "D:\\fitme\\lib\\features\\nutrition\\widgets\\log_sheet.dart", "source_location": null}], "edges": [{"source": "d_fitme_lib_features_nutrition_widgets_log_sheet_dart", "target": "d_fitme_lib_features_nutrition_widgets_log_sheet_dart_logsheet", "relation": "defines", "confidence": "EXTRACTED", "confidence_score": 1.0, "source_file": "D:\\fitme\\lib\\features\\nutrition\\widgets\\log_sheet.dart", "source_location": null, "weight": 1.0}, {"source": "d_fitme_lib_features_nutrition_widgets_log_sheet_dart", "target": "d_fitme_lib_features_nutrition_widgets_log_sheet_dart_logsheetstate", "relation": "defines", "confidence": "EXTRACTED", "confidence_score": 1.0, "source_file": "D:\\fitme\\lib\\features\\nutrition\\widgets\\log_sheet.dart", "source_location": null, "weight": 1.0}, {"source": "d_fitme_lib_features_nutrition_widgets_log_sheet_dart", "target": "d_fitme_lib_features_nutrition_widgets_log_sheet_dart_searchresults", "relation": "defines", "confidence": "EXTRACTED", "confidence_score": 1.0, "source_file": "D:\\fitme\\lib\\features\\nutrition\\widgets\\log_sheet.dart", "source_location": null, "weight": 1.0}, {"source": "d_fitme_lib_features_nutrition_widgets_log_sheet_dart", "target": "d_fitme_lib_features_nutrition_widgets_log_sheet_dart_recentstab", "relation": "defines", "confidence": "EXTRACTED", "confidence_score": 1.0, "source_file": "D:\\fitme\\lib\\features\\nutrition\\widgets\\log_sheet.dart", "source_location": null, "weight": 1.0}, {"source": "d_fitme_lib_features_nutrition_widgets_log_sheet_dart", "target": "d_fitme_lib_features_nutrition_widgets_log_sheet_dart_customstab", "relation": "defines", "confidence": "EXTRACTED", "confidence_score": 1.0, "source_file": "D:\\fitme\\lib\\features\\nutrition\\widgets\\log_sheet.dart", "source_location": null, "weight": 1.0}, {"source": "d_fitme_lib_features_nutrition_widgets_log_sheet_dart", "target": "d_fitme_lib_features_nutrition_widgets_log_sheet_dart_listheader", "relation": "defines", "confidence": "EXTRACTED", "confidence_score": 1.0, "source_file": "D:\\fitme\\lib\\features\\nutrition\\widgets\\log_sheet.dart", "source_location": null, "weight": 1.0}, {"source": "d_fitme_lib_features_nutrition_widgets_log_sheet_dart", "target": "d_fitme_lib_features_nutrition_widgets_log_sheet_dart_custommealtile", "relation": "defines", "confidence": "EXTRACTED", "confidence_score": 1.0, "source_file": "D:\\fitme\\lib\\features\\nutrition\\widgets\\log_sheet.dart", "source_location": null, "weight": 1.0}, {"source": "d_fitme_lib_features_nutrition_widgets_log_sheet_dart", "target": "d_fitme_lib_features_nutrition_widgets_log_sheet_dart_foodresulttile", "relation": "defines", "confidence": "EXTRACTED", "confidence_score": 1.0, "source_file": "D:\\fitme\\lib\\features\\nutrition\\widgets\\log_sheet.dart", "source_location": null, "weight": 1.0}, {"source": "d_fitme_lib_features_nutrition_widgets_log_sheet_dart", "target": "d_fitme_lib_features_nutrition_widgets_log_sheet_dart_heartbutton", "relation": "defines", "confidence": "EXTRACTED", "confidence_score": 1.0, "source_file": "D:\\fitme\\lib\\features\\nutrition\\widgets\\log_sheet.dart", "source_location": null, "weight": 1.0}, {"source": "d_fitme_lib_features_nutrition_widgets_log_sheet_dart", "target": "d_fitme_lib_features_nutrition_widgets_log_sheet_dart_show", "relation": "defines", "confidence": "EXTRACTED", "confidence_score": 1.0, "source_file": "D:\\fitme\\lib\\features\\nutrition\\widgets\\log_sheet.dart", "source_location": null, "weight": 1.0}, {"source": "d_fitme_lib_features_nutrition_widgets_log_sheet_dart", "target": "d_fitme_lib_features_nutrition_widgets_log_sheet_dart_initstate", "relation": "defines", "confidence": "EXTRACTED", "confidence_score": 1.0, "source_file": "D:\\fitme\\lib\\features\\nutrition\\widgets\\log_sheet.dart", "source_location": null, "weight": 1.0}, {"source": "d_fitme_lib_features_nutrition_widgets_log_sheet_dart", "target": "d_fitme_lib_features_nutrition_widgets_log_sheet_dart_dispose", "relation": "defines", "confidence": "EXTRACTED", "confidence_score": 1.0, "source_file": "D:\\fitme\\lib\\features\\nutrition\\widgets\\log_sheet.dart", "source_location": null, "weight": 1.0}, {"source": "d_fitme_lib_features_nutrition_widgets_log_sheet_dart", "target": "d_fitme_lib_features_nutrition_widgets_log_sheet_dart_onsearchchanged", "relation": "defines", "confidence": "EXTRACTED", "confidence_score": 1.0, "source_file": "D:\\fitme\\lib\\features\\nutrition\\widgets\\log_sheet.dart", "source_location": null, "weight": 1.0}, {"source": "d_fitme_lib_features_nutrition_widgets_log_sheet_dart", "target": "d_fitme_lib_features_nutrition_widgets_log_sheet_dart_onfoodtapped", "relation": "defines", "confidence": "EXTRACTED", "confidence_score": 1.0, "source_file": "D:\\fitme\\lib\\features\\nutrition\\widgets\\log_sheet.dart", "source_location": null, "weight": 1.0}, {"source": "d_fitme_lib_features_nutrition_widgets_log_sheet_dart", "target": "d_fitme_lib_features_nutrition_widgets_log_sheet_dart_togglefav", "relation": "defines", "confidence": "EXTRACTED", "confidence_score": 1.0, "source_file": "D:\\fitme\\lib\\features\\nutrition\\widgets\\log_sheet.dart", "source_location": null, "weight": 1.0}, {"source": "d_fitme_lib_features_nutrition_widgets_log_sheet_dart", "target": "d_fitme_lib_features_nutrition_widgets_log_sheet_dart_build", "relation": "defines", "confidence": "EXTRACTED", "confidence_score": 1.0, "source_file": "D:\\fitme\\lib\\features\\nutrition\\widgets\\log_sheet.dart", "source_location": null, "weight": 1.0}, {"source": "d_fitme_lib_features_nutrition_widgets_log_sheet_dart", "target": "d_fitme_lib_features_nutrition_widgets_log_sheet_dart_container", "relation": "defines", "confidence": "EXTRACTED", "confidence_score": 1.0, "source_file": "D:\\fitme\\lib\\features\\nutrition\\widgets\\log_sheet.dart", "source_location": null, "weight": 1.0}, {"source": "d_fitme_lib_features_nutrition_widgets_log_sheet_dart", "target": "d_fitme_lib_features_nutrition_widgets_log_sheet_dart_sizedbox", "relation": "defines", "confidence": "EXTRACTED", "confidence_score": 1.0, "source_file": "D:\\fitme\\lib\\features\\nutrition\\widgets\\log_sheet.dart", "source_location": null, "weight": 1.0}, {"source": "d_fitme_lib_features_nutrition_widgets_log_sheet_dart", "target": "d_fitme_lib_features_nutrition_widgets_log_sheet_dart_padding", "relation": "defines", "confidence": "EXTRACTED", "confidence_score": 1.0, "source_file": "D:\\fitme\\lib\\features\\nutrition\\widgets\\log_sheet.dart", "source_location": null, "weight": 1.0}, {"source": "d_fitme_lib_features_nutrition_widgets_log_sheet_dart", "target": "d_fitme_lib_features_nutrition_widgets_log_sheet_dart_icon", "relation": "defines", "confidence": "EXTRACTED", "confidence_score": 1.0, "source_file": "D:\\fitme\\lib\\features\\nutrition\\widgets\\log_sheet.dart", "source_location": null, "weight": 1.0}, {"source": "d_fitme_lib_features_nutrition_widgets_log_sheet_dart", "target": "d_fitme_lib_features_nutrition_widgets_log_sheet_dart_spacer", "relation": "defines", "confidence": "EXTRACTED", "confidence_score": 1.0, "source_file": "D:\\fitme\\lib\\features\\nutrition\\widgets\\log_sheet.dart", "source_location": null, "weight": 1.0}, {"source": "d_fitme_lib_features_nutrition_widgets_log_sheet_dart", "target": "d_fitme_lib_features_nutrition_widgets_log_sheet_dart_textstyle", "relation": "defines", "confidence": "EXTRACTED", "confidence_score": 1.0, "source_file": "D:\\fitme\\lib\\features\\nutrition\\widgets\\log_sheet.dart", "source_location": null, "weight": 1.0}, {"source": "d_fitme_lib_features_nutrition_widgets_log_sheet_dart", "target": "d_fitme_lib_features_nutrition_widgets_log_sheet_dart_center", "relation": "defines", "confidence": "EXTRACTED", "confidence_score": 1.0, "source_file": "D:\\fitme\\lib\\features\\nutrition\\widgets\\log_sheet.dart", "source_location": null, "weight": 1.0}, {"source": "d_fitme_lib_features_nutrition_widgets_log_sheet_dart", "target": "d_fitme_lib_features_nutrition_widgets_log_sheet_dart_stack", "relation": "defines", "confidence": "EXTRACTED", "confidence_score": 1.0, "source_file": "D:\\fitme\\lib\\features\\nutrition\\widgets\\log_sheet.dart", "source_location": null, "weight": 1.0}, {"source": "d_fitme_lib_features_nutrition_widgets_log_sheet_dart", "target": "dart_async", "relation": "imports", "confidence": "EXTRACTED", "confidence_score": 1.0, "source_file": "D:\\fitme\\lib\\features\\nutrition\\widgets\\log_sheet.dart", "source_location": null, "weight": 1.0}, {"source": "d_fitme_lib_features_nutrition_widgets_log_sheet_dart", "target": "package_flutter_material_dart", "relation": "imports", "confidence": "EXTRACTED", "confidence_score": 1.0, "source_file": "D:\\fitme\\lib\\features\\nutrition\\widgets\\log_sheet.dart", "source_location": null, "weight": 1.0}, {"source": "d_fitme_lib_features_nutrition_widgets_log_sheet_dart", "target": "package_flutter_services_dart", "relation": "imports", "confidence": "EXTRACTED", "confidence_score": 1.0, "source_file": "D:\\fitme\\lib\\features\\nutrition\\widgets\\log_sheet.dart", "source_location": null, "weight": 1.0}, {"source": "d_fitme_lib_features_nutrition_widgets_log_sheet_dart", "target": "package_flutter_riverpod_flutter_riverpod_dart", "relation": "imports", "confidence": "EXTRACTED", "confidence_score": 1.0, "source_file": "D:\\fitme\\lib\\features\\nutrition\\widgets\\log_sheet.dart", "source_location": null, "weight": 1.0}, {"source": "d_fitme_lib_features_nutrition_widgets_log_sheet_dart", "target": "core_theme_app_theme_dart", "relation": "imports", "confidence": "EXTRACTED", "confidence_score": 1.0, "source_file": "D:\\fitme\\lib\\features\\nutrition\\widgets\\log_sheet.dart", "source_location": null, "weight": 1.0}, {"source": "d_fitme_lib_features_nutrition_widgets_log_sheet_dart", "target": "models_food_item_dart", "relation": "imports", "confidence": "EXTRACTED", "confidence_score": 1.0, "source_file": "D:\\fitme\\lib\\features\\nutrition\\widgets\\log_sheet.dart", "source_location": null, "weight": 1.0}, {"source": "d_fitme_lib_features_nutrition_widgets_log_sheet_dart", "target": "providers_nutrition_provider_dart", "relation": "imports", "confidence": "EXTRACTED", "confidence_score": 1.0, "source_file": "D:\\fitme\\lib\\features\\nutrition\\widgets\\log_sheet.dart", "source_location": null, "weight": 1.0}, {"source": "d_fitme_lib_features_nutrition_widgets_log_sheet_dart", "target": "services_food_search_service_dart", "relation": "imports", "confidence": "EXTRACTED", "confidence_score": 1.0, "source_file": "D:\\fitme\\lib\\features\\nutrition\\widgets\\log_sheet.dart", "source_location": null, "weight": 1.0}, {"source": "d_fitme_lib_features_nutrition_widgets_log_sheet_dart", "target": "screens_quantity_selection_screen_dart", "relation": "imports", "confidence": "EXTRACTED", "confidence_score": 1.0, "source_file": "D:\\fitme\\lib\\features\\nutrition\\widgets\\log_sheet.dart", "source_location": null, "weight": 1.0}, {"source": "d_fitme_lib_features_nutrition_widgets_log_sheet_dart", "target": "screens_favorites_screen_dart", "relation": "imports", "confidence": "EXTRACTED", "confidence_score": 1.0, "source_file": "D:\\fitme\\lib\\features\\nutrition\\widgets\\log_sheet.dart", "source_location": null, "weight": 1.0}, {"source": "d_fitme_lib_features_nutrition_widgets_log_sheet_dart", "target": "barcode_scanner_screen_dart", "relation": "imports", "confidence": "EXTRACTED", "confidence_score": 1.0, "source_file": "D:\\fitme\\lib\\features\\nutrition\\widgets\\log_sheet.dart", "source_location": null, "weight": 1.0}, {"source": "d_fitme_lib_features_nutrition_widgets_log_sheet_dart", "target": "custom_meal_form_dart", "relation": "imports", "confidence": "EXTRACTED", "confidence_score": 1.0, "source_file": "D:\\fitme\\lib\\features\\nutrition\\widgets\\log_sheet.dart", "source_location": null, "weight": 1.0}]}